flake8_deprecation.py
flake8_deprecation-1.0.1.dist-info/licenses/LICENSE
flake8_deprecation-1.0.1.dist-info/METADATA
flake8_deprecation-1.0.1.dist-info/WHEEL
flake8_deprecation-1.0.1.dist-info/entry_points.txt
flake8_deprecation-1.0.1.dist-info/top_level.txt
flake8_deprecation-1.0.1.dist-info/RECORD
